setup.py
pyscraper_framework/__init__.py
pyscraper_framework/app.py
pyscraper_framework/config.py
pyscraper_framework/worker.py
pyscraper_framework.egg-info/PKG-INFO
pyscraper_framework.egg-info/SOURCES.txt
pyscraper_framework.egg-info/dependency_links.txt
pyscraper_framework.egg-info/entry_points.txt
pyscraper_framework.egg-info/requires.txt
pyscraper_framework.egg-info/top_level.txt
pyscraper_framework/../README.md
pyscraper_framework/../VERSION
pyscraper_framework/../requirements.txt
pyscraper_framework/lib/__init__.py
pyscraper_framework/lib/etl_job.py
pyscraper_framework/lib/extractor.py
pyscraper_framework/lib/loader.py
pyscraper_framework/lib/pipeline.py
pyscraper_framework/lib/pipeline_manager.py
pyscraper_framework/lib/transformer.py
pyscraper_framework/templates/index.jade
pyscraper_framework/templates/layout.jade
pyscraper_framework/templates/pipeline.jade
pyscraper_framework/templates/pipeline_start.jade
pyscraper_framework/templates/pipelines.jade